pyncthing/__init__.py
pyncthing/api.py
pyncthing/api_cluster.py
pyncthing/api_config.py
pyncthing/api_db.py
pyncthing/api_debug.py
pyncthing/api_events.py
pyncthing/api_folder.py
pyncthing/api_noauth.py
pyncthing/api_stats.py
pyncthing/api_svc.py
pyncthing/api_system.py
pyncthing/syncthing.py
pyncthing-0.1.0.dist-info/METADATA
pyncthing-0.1.0.dist-info/WHEEL
pyncthing-0.1.0.dist-info/RECORD
