Metadata-Version: 2.1
Name: pyncthing
Version: 0.1.0
Summary: Python bindings to the Syncthing API
License: GPLv3
Author: Félix Piédallu
Author-email: felix@piedallu.me
Requires-Python: >=3.8,<4.0
Classifier: License :: Other/Proprietary License
Classifier: Programming Language :: Python :: 3
Classifier: Programming Language :: Python :: 3.8
Classifier: Programming Language :: Python :: 3.9
Classifier: Programming Language :: Python :: 3.10
Classifier: Programming Language :: Python :: 3.11
Requires-Dist: requests (>=2.31.0,<3.0.0)
